<?xml version="1.0" encoding="utf-8"?>
<object name="portal_catalog">

  <!-- Needed for additional_contact_info in Person content type -->

  <index meta_type="FieldIndex"
         name="contact_building"
  >
    <indexed_attr value="contact_building" />
  </index>
  <column value="contact_building" />

  <index meta_type="FieldIndex"
         name="contact_room"
  >
    <indexed_attr value="contact_room" />
  </index>

  <index meta_type="FieldIndex"
         name="organisational_unit_reference"
  >
    <indexed_attr value="organisational_unit_reference" />
  </index>


  <index meta_type="FieldIndex"
         name="location_reference"
  >
    <indexed_attr value="location_reference" />
  </index>

  <column value="contact_room" />
  <column value="location_reference" />
  <column value="organisational_unit_reference" />
  <column value="job_title" />

</object>
